{
  "name": "SHADOW CRYPT",
  "theme": "bbc",
  "gravity": 0.016,
  "fuel": 2900,
  "spawn": {
    "x": 388,
    "y": 60
  },
  "exitY": 45,
  "polygons": [
    [
      [
        0,
        0
      ],
      [
        289,
        0
      ],
      [
        268,
        52
      ],
      [
        256,
        103
      ],
      [
        270,
        145
      ],
      [
        245,
        185
      ],
      [
        245,
        243
      ],
      [
        249,
        283
      ],
      [
        203,
        328
      ],
      [
        183,
        377
      ],
      [
        176,
        413
      ],
      [
        191,
        450
      ],
      [
        201,
        498
      ],
      [
        246,
        535
      ],
      [
        238,
        597
      ],
      [
        247,
        664
      ],
      [
        194,
        711
      ],
      [
        189,
        769
      ],
      [
        162,
        814
      ],
      [
        0,
        814
      ]
    ],
    [
      [
        691,
        0
      ],
      [
        488,
        0
      ],
      [
        514,
        55
      ],
      [
        519,
        99
      ],
      [
        520,
        145
      ],
      [
        522,
        221
      ],
      [
        488,
        283
      ],
      [
        517,
        331
      ],
      [
        506,
        369
      ],
      [
        511,
        413
      ],
      [
        498,
        458
      ],
      [
        483,
        489
      ],
      [
        463,
        535
      ],
      [
        482,
        603
      ],
      [
        476,
        664
      ],
      [
        530,
        711
      ],
      [
        534,
        764
      ],
      [
        561,
        814
      ],
      [
        691,
        814
      ]
    ],
    [
      [
        0,
        814
      ],
      [
        691,
        814
      ],
      [
        691,
        864
      ],
      [
        0,
        864
      ]
    ],
    [
      [
        329,
        799
      ],
      [
        413,
        799
      ],
      [
        401,
        814
      ],
      [
        341,
        814
      ]
    ]
  ],
  "entities": [
    {
      "type": "pod",
      "x": 371,
      "y": 784
    },
    {
      "type": "reactor",
      "x": 255,
      "y": 796
    },
    {
      "type": "turret",
      "x": 469,
      "y": 664,
      "angle": 3.141592653589793
    },
    {
      "type": "turret",
      "x": 256,
      "y": 283,
      "angle": 0
    },
    {
      "type": "turret",
      "x": 456,
      "y": 535,
      "angle": 3.141592653589793
    },
    {
      "type": "fuel",
      "x": 438,
      "y": 404,
      "capacity": 450
    },
    {
      "type": "fuel",
      "x": 351,
      "y": 651,
      "capacity": 450
    },
    {
      "type": "fuel",
      "x": 330,
      "y": 523,
      "capacity": 450
    }
  ],
  "difficulty": "LEICHT"
}